rxn_biocatalysis_tools/__init__.py
rxn_biocatalysis_tools/chemical_reaction.py
rxn_biocatalysis_tools/enzymatic_reaction.py
rxn_biocatalysis_tools/tokenizer.py
rxn_biocatalysis_tools/utils.py
rxn_biocatalysis_tools-1.0.1.data/scripts/rbt-canonicalize.py
rxn_biocatalysis_tools-1.0.1.data/scripts/rbt-evaluate.py
rxn_biocatalysis_tools-1.0.1.data/scripts/rbt-extract.py
rxn_biocatalysis_tools-1.0.1.data/scripts/rbt-preprocess.py
rxn_biocatalysis_tools-1.0.1.data/scripts/rbt-randomize-ec.py
test/__init__.py
test/test_enzymatic_reaction.py
test/test_tokenizer.py
rxn_biocatalysis_tools-1.0.1.dist-info/LICENSE
rxn_biocatalysis_tools-1.0.1.dist-info/METADATA
rxn_biocatalysis_tools-1.0.1.dist-info/WHEEL
rxn_biocatalysis_tools-1.0.1.dist-info/top_level.txt
rxn_biocatalysis_tools-1.0.1.dist-info/RECORD
