Metadata-Version: 2.1
Name: rxn-biocatalysis-tools
Version: 1.0.1
Summary: Tools for pre-processing and evaluating data associated with biocatalysis models.
Home-page: https://github.com/rxn4chemistry/biocatalysis-model
Author: Daniel Probst, Matteo Manica, Yves Gaetan Nana @ IBM
Author-email: dpr@zurich.ibm.com, tte@zurich.ibm.com, yna@zurich.ibm.vom
License: UNKNOWN
Platform: UNKNOWN
Classifier: Intended Audience :: Developers
Classifier: Intended Audience :: Science/Research
Classifier: Programming Language :: Python :: 3.6
Classifier: Programming Language :: Python :: 3.7
Classifier: Programming Language :: Python :: 3.8
Classifier: Topic :: Software Development :: Libraries :: Python Modules
Requires-Python: >=3.6
License-File: LICENSE
Provides-Extra: dev
Requires-Dist: pytest (==6.1.2) ; extra == 'dev'
Requires-Dist: pytest-cov (==2.10.1) ; extra == 'dev'
Requires-Dist: flake8 (==3.8.4) ; extra == 'dev'
Requires-Dist: black (==20.8b1) ; extra == 'dev'
Requires-Dist: mypy (==0.782) ; extra == 'dev'
